hkpy/__init__.py
hkpy/py.typed
hkpy/common/__init__.py
hkpy/common/result_set.py
hkpy/hkbase/__init__.py
hkpy/hkbase/hkbase.py
hkpy/hkbase/hkobserverfactory.py
hkpy/hkbase/hkrepository.py
hkpy/hkbase/hktransaction.py
hkpy/hkbase/query.py
hkpy/hkbase/query_management.py
hkpy/hkbase/observer/__init__.py
hkpy/hkbase/observer/notification.py
hkpy/hkbase/observer/clients/__init__.py
hkpy/hkbase/observer/clients/configurableobserverclient.py
hkpy/hkbase/observer/clients/observerclient.py
hkpy/hkbase/observer/clients/rabbitmqobserverclient.py
hkpy/hkbase/observer/clients/restobserverclient.py
hkpy/hklib/__init__.py
hkpy/hklib/anchor.py
hkpy/hklib/connector.py
hkpy/hklib/entity.py
hkpy/hklib/graph.py
hkpy/hklib/graphbuilder.py
hkpy/hklib/link.py
hkpy/hklib/node.py
hkpy/hklib/fi/__init__.py
hkpy/hklib/fi/fi.py
hkpy/hklib/fi/fianchor.py
hkpy/hklib/fi/fioperator.py
hkpy/hklib/fi/fiparser.py
hkpy/hklib/fi/grammar.py
hkpy/hkpyo/__init__.py
hkpy/hkpyo/converters/HKOReaderHKG.py
hkpy/hkpyo/converters/HKOWriterHKG.py
hkpy/hkpyo/converters/__init__.py
hkpy/hkpyo/converters/constants.py
hkpy/hkpyo/converters/utils.py
hkpy/hkpyo/hkb/__init__.py
hkpy/hkpyo/hkb/hkbo.py
hkpy/hkpyo/hkb/hkbo_simple.py
hkpy/hkpyo/model/__init__.py
hkpy/hkpyo/model/hko_model.py
hkpy/hkpyo/reasoners/__init__.py
hkpy/hkpyo/reasoners/simple_reasoner.py
hkpy/oops/__init__.py
hkpy/oops/oops.py
hkpy/utils/__init__.py
hkpy/utils/constants.py
hkpy/utils/misc.py
hkpy-2.11.3.dist-info/LICENSE
hkpy-2.11.3.dist-info/METADATA
hkpy-2.11.3.dist-info/WHEEL
hkpy-2.11.3.dist-info/top_level.txt
hkpy-2.11.3.dist-info/RECORD
