Metadata-Version: 2.1
Name: hkpy
Version: 2.11.3
Summary: A Python module to create software abstraction for accessing hyperknowledge graphs
Home-page: https://github.com/ibm-hyperknowledge/hkpy
Author: IBM Research Brazil
Author-email: mmoreno@br.ibm.com
License: MIT
Keywords: Hyperknowlede,Knowledge Engineering
Classifier: Development Status :: 2 - Pre-Alpha
Classifier: Intended Audience :: Science/Research
Classifier: Intended Audience :: Developers
Classifier: Topic :: Software Development :: Build Tools
Classifier: Programming Language :: Python :: 3.6
Classifier: Programming Language :: Python :: 3.7
Classifier: Programming Language :: Python :: 3.8
Requires-Python: >=3.6
License-File: LICENSE
Requires-Dist: requests
Requires-Dist: pika
Requires-Dist: Flask
Requires-Dist: flask-cors
Requires-Dist: PyJWT
Requires-Dist: urllib3
Requires-Dist: idna
Requires-Dist: certifi
Requires-Dist: lark
